wright_plans/__init__.py
wright_plans/_constants.py
wright_plans/_messages.py
wright_plans/_plans.py
wright_plans/_units.py
wright_plans/attune.py
wright_plans-2022.7.0.dist-info/LICENSE
wright_plans-2022.7.0.dist-info/WHEEL
wright_plans-2022.7.0.dist-info/METADATA
wright_plans-2022.7.0.dist-info/RECORD
