Metadata-Version: 2.1
Name: wright_plans
Version: 2022.7.0
Summary: Bluesky plans and utilities to provide functionality that the Wright Group needs.
Home-page: https://github.com/wright-group/bluesky-wright
Author: Kyle Sunden
Author-email: contact@ksunden.space
Requires-Python: >=3.9
Classifier: License :: OSI Approved :: MIT License
Requires-Dist: bluesky
Requires-Dist: pint
Requires-Dist: toolz
Requires-Dist: attune ; extra == "attune"
Requires-Dist: numpy ; extra == "attune"
Requires-Dist: cycler ; extra == "attune"
Requires-Dist: pytest ; extra == "tests"
Requires-Dist: yaqd-fakes ; extra == "tests"
Requires-Dist: yaqd-attune ; extra == "tests"
Requires-Dist: yaqc-bluesky>=2022.4.1 ; extra == "tests"
Requires-Dist: numpy ; extra == "tests"
Provides-Extra: attune
Provides-Extra: tests
